<keymap version="1" name="macOS copy" parent="Mac OS X 10.5+">
  <action id="Arrangement.Rule.Add">
    <keyboard-shortcut first-keystroke="ctrl enter" />
  </action>
  <action id="Back">
    <keyboard-shortcut first-keystroke="meta open_bracket" />
    <keyboard-shortcut first-keystroke="meta alt left" />
    <mouse-shortcut keystroke="button4" />
    <keyboard-shortcut first-keystroke="meta o" />
  </action>
  <action id="DatabaseView.PropertiesAction" />
  <action id="FileChooser.NewFolder" />
  <action id="Generate">
    <keyboard-shortcut first-keystroke="ctrl enter" />
  </action>
  <action id="GotoChangedFile" />
  <action id="GotoClass">
    <keyboard-shortcut first-keystroke="meta n" />
  </action>
  <action id="GotoFile">
    <keyboard-shortcut first-keystroke="shift meta o" />
    <keyboard-shortcut first-keystroke="shift meta n" />
  </action>
  <action id="NewElement">
    <keyboard-shortcut first-keystroke="ctrl enter" />
  </action>
  <action id="NewScratchFile" />
  <action id="ParameterInfo">
    <keyboard-shortcut first-keystroke="meta p" />
    <keyboard-shortcut first-keystroke="meta i" />
  </action>
  <action id="RemoteHost.NewRemoteItem">
    <keyboard-shortcut first-keystroke="ctrl enter" />
  </action>
</keymap>